LICENCE
README.md
setup.py
joyoussync/__init__.py
joyoussync/apps.py
joyoussync/models.py
joyoussync/utils.py
joyoussync/wagtail_hooks.py
joyoussync.egg-info/PKG-INFO
joyoussync.egg-info/SOURCES.txt
joyoussync.egg-info/dependency_links.txt
joyoussync.egg-info/requires.txt
joyoussync.egg-info/top_level.txt
joyoussync/migrations/0001_initial.py
joyoussync/migrations/__init__.py