Metadata-Version: 2.1
Name: joyoussync
Version: 0.1.2.1
Summary: A small Django app for adding calendar sync support to ls.joyous
Home-page: https://github.com/frcl/joyoussync
Author: Lars Franke
Author-email: frcl@mailbox.org
License: MIT
Platform: UNKNOWN
License-File: LICENCE
